{
  "table": [
    {
      "cell1": "प्रशासन",
      "cell2": "कार्यालय/आवास",
      "cell3": "मोबाइल संख्या",
      "cell4": "   ",
      "cell5": "title"
    },
    {
      "cell1": "आयुक्त, भागलपुर प्रमंडल, भागलपुर",
      "cell2": " ",
      "cell3": "9473191433",
      "cell4": "  ",
      "cell5": " "
    },
    {
      "cell1": "पुलिस महानिरीक्षक, भागलपुर",
      "cell2": " ",
      "cell3": "9431822953",
      "cell4": "  ",
      "cell5": " "
    },
    {
      "cell1": "पुलिस उप महा निरीक्षक, भागलपुर",
      "cell2": " ",
      "cell3": "9431822958",
      "cell4": "  ",
      "cell5": " "
    },
    {
      "cell1": "जिलाधिकारी, भागलपुर",
      "cell2": " ",
      "cell3": "9473191381",
      "cell4": "  ",
      "cell5": " "
    },
    {
      "cell1": "वरीय पुलिस अधीक्षक, भागलपुर",
      "cell2": " ",
      "cell3": "9431800003",
      "cell4": "  ",
      "cell5": " "
    },
    {
      "cell1": "पुलिस अधीक्षक, नवगछिया",
      "cell2": " ",
      "cell3": "9431800005",
      "cell4": "  ",
      "cell5": " "
    },
    {
      "cell1": "उप विकास आयुक्त, भागलपुर",
      "cell2": " ",
      "cell3": "9431818374",
      "cell4": "  ",
      "cell5": " "
    },
    {
      "cell1": "अपर समाहर्त्ता, भागलपुर",
      "cell2": " ",
      "cell3": "9473191382",
      "cell4": "  ",
      "cell5": " "
    },
    {
      "cell1": "अपर समाहर्त्ता, विभागीय जाँच-सह-मेला-दंडाधिकारी, भागलपुर",
      "cell2": " ",
      "cell3": "7004438383",
      "cell4": "  ",
      "cell5": " "
    },
    {
      "cell1": "अनुमंडल पदाधिकारी, भागलपुर",
      "cell2": " ",
      "cell3": "9473191383",
      "cell4": "  ",
      "cell5": " "
    },
    {
      "cell1": "भूमि सुधार उप समाहर्त्ता, सदर, भागलपुर",
      "cell2": " ",
      "cell3": "8544412312",
      "cell4": "  ",
      "cell5": " "
    },
    {
      "cell1": "जिला परिवहन पदाधिकारी, भागलपुर",
      "cell2": " ",
      "cell3": "9955238499",
      "cell4": "  ",
      "cell5": " "
    },
    {
      "cell1": "असैनिक शल्य चिकित्सक-सह-मुख्या चिकित्सा पदाधिकारी, भागलपुर",
      "cell2": " ",
      "cell3": "9470003118",
      "cell4": "  ",
      "cell5": " "
    },
    {
      "cell1": "जिला जन संपर्क पदाधिकारी, भागलपुर",
      "cell2": " ",
      "cell3": "9430279088",
      "cell4": "  ",
      "cell5": " "
    },
    {
      "cell1": "पुलिस उपाधीक्षक,नगर, भागलपुर",
      "cell2": " ",
      "cell3": "9431800031",
      "cell4": "  ",
      "cell5": " "
    },
    {
      "cell1": "पुलिस उपाधीक्षक, विधि-व्यवस्था, भागलपुर",
      "cell2": " ",
      "cell3": "9431822601",
      "cell4": "  ",
      "cell5": " "
    },
    {
      "cell1": "पुलिस उपाधीक्षक (मुख्यालय),  भागलपुर",
      "cell2": " ",
      "cell3": "9431822604",
      "cell4": "  ",
      "cell5": " "
    },
    {
      "cell1": "पुलिस उपाधीक्षक, कहलगांव ",
      "cell2": " ",
      "cell3": "9431800032",
      "cell4": "  ",
      "cell5": " "
    },
    {
      "cell1": "पुलिस उपाधीक्षक,  नवगछिया",
      "cell2": " ",
      "cell3": "9431800029",
      "cell4": "  ",
      "cell5": " "
    },
    {
      "cell1": "पुलिस उपाधीक्षक (मुख्यालय), नवगछिया",
      "cell2": " ",
      "cell3": "9431092990",
      "cell4": "  ",
      "cell5": " "
    },
    {
      "cell1": "पु०अ०नि० (सीढ़ी घाट सुल्तानगंज)",
      "cell2": " ",
      "cell3": "7480004973",
      "cell4": "  ",
      "cell5": " "
    },
    {
      "cell1": "स०अ०नि० (सीढ़ी घाट सुल्तानगंज)",
      "cell2": " ",
      "cell3": "995555047",
      "cell4": "  ",
      "cell5": " "
    },
    {
      "cell1": "स०अ०नि० (जहाज घाट सुल्तानगंज)",
      "cell2": " ",
      "cell3": "9801445456",
      "cell4": "  ",
      "cell5": "  "
    },
    {
      "cell1": "स०अ०नि० (ऐ०के० गोपालन० कॉलेज०/बाथ/बेलारी  सुल्तानगंज)",
      "cell2": " ",
      "cell3": "9473197533",
      "cell4": "  ",
      "cell5": "  "
    },
    {
      "cell1": "स०अ०नि० (कृष्णगढ़ ओवरब्रिज विश्राम स्थल  सुल्तानगंज)",
      "cell2": " ",
      "cell3": "934442672",
      "cell4": "  ",
      "cell5": "  "
    },
    {
      "cell1": "स०अ०नि० (रेलवे स्टेशन  सुल्तानगंज)",
      "cell2": " ",
      "cell3": "8825193310",
      "cell4": "  ",
      "cell5": "  "
    },
    {
      "cell1": "पु०अ०नि० (बेलहर थाना अंतर्गत धौरी धर्मशाला) बांका",
      "cell2": " ",
      "cell3": "9473197537",
      "cell4": "  ",
      "cell5": "  "
    },
    {
      "cell1": "पु०नि० (जिलेबिया नियंत्रण कक्ष एवं धर्मशाला) बांका",
      "cell2": " ",
      "cell3": "9430927934",
      "cell4": "  ",
      "cell5": "  "
    },
    {
      "cell1": "पु०अ०नि० (कटोरिया नियंत्रण कक्ष ) बांका",
      "cell2": " ",
      "cell3": "9905276995",
      "cell4": "  ",
      "cell5": "  "
    },
    {
      "cell1": "लोक स्वास्थ्य प्रमंडल भागलपुर पश्चिम",
      "cell2": " ",
      "cell3": " ",
      "cell4": "  ",
      "cell5": "title"
    },
    {
      "cell1": "ई० सुनील कुमार सुमन ",
      "cell2": "कार्यपालक अभियंता ",
      "cell3": "8544428969",
      "cell4": "  ",
      "cell5": " "
    },
    {
      "cell1": "ई० दिलीप कुमार चौधरी",
      "cell2": "सहायक अभियंता ",
      "cell3": "8544428740",
      "cell4": "  ",
      "cell5": " "
    },
    {
      "cell1": "ई० नसीम नज़र",
      "cell2": "सहायक अभियंता ",
      "cell3": "8544428741",
      "cell4": "  ",
      "cell5": " "
    },
    {
      "cell1": "ई० दिनेश कुमार सिंह ",
      "cell2": "कनीय अभियंता ",
      "cell3": "9471227822",
      "cell4": "  ",
      "cell5": " "
    },
    {
      "cell1": "ई० महेंद्र चौधरी ",
      "cell2": "कनीय अभियंता ",
      "cell3": "9934825814",
      "cell4": "  ",
      "cell5": " "
    },
    {
      "cell1": "ई० विकाश कुमार गुप्ता ",
      "cell2": "कनीय अभियंता ",
      "cell3": "9155547292",
      "cell4": "  ",
      "cell5": " "
    },
    {
      "cell1": "ई० नीरज कुमार",
      "cell2": "कनीय अभियंता ",
      "cell3": "9431891865",
      "cell4": "  ",
      "cell5": " "
    },
    {
      "cell1": "ई० सुश्री शिप्रा चौधरी",
      "cell2": "कनीय अभियंता ",
      "cell3": "7542808736",
      "cell4": "  ",
      "cell5": " "
    }
  ]
}