{
  "table": [
    {
      "cell1": "Sl. No.",
      "cell2": "Name",
      "cell3": "Designation",
      "cell4": "Mobile No.",
      "cell5": " "
    },
    {
      "cell1": "1",
      "cell2": "Ganesh Jee Ojha ",
      "cell3": "Inspector",
      "cell4": "9955568113",
      "cell5": " "
    },
    {
      "cell1": " ",
      "cell2": " ",
      "cell3": " ",
      "cell4": "9470002753",
      "cell5": " "
    },
    {
      "cell1": "2",
      "cell2": "Prahlad Singh",
      "cell3": "Sub-Inspector",
      "cell4": "9473386523",
      "cell5": " "
    },
    {
      "cell1": "3",
      "cell2": "Surendra Mandal",
      "cell3": "Head Constable",
      "cell4": "9801228254",
      "cell5": " "
    },
    {
      "cell1": "4",
      "cell2": "Ramesh Kumar singh",
      "cell3": "Constable",
      "cell4": "9534870063",
      "cell5": " "
    }
  ]
}